openfisca_nsw_base/__init__.py
openfisca_nsw_base/entities.py
openfisca_nsw_base/parameters/__init__.py
openfisca_nsw_base/reforms/__init__.py
openfisca_nsw_base/situation_examples/__init__.py
openfisca_nsw_base-0.8.0.data/data/share/openfisca/openfisca_nsw_base/CHANGELOG.md
openfisca_nsw_base-0.8.0.data/data/share/openfisca/openfisca_nsw_base/LICENSE
openfisca_nsw_base-0.8.0.data/data/share/openfisca/openfisca_nsw_base/README.md
openfisca_nsw_base-0.8.0.dist-info/LICENSE
openfisca_nsw_base-0.8.0.dist-info/METADATA
openfisca_nsw_base-0.8.0.dist-info/WHEEL
openfisca_nsw_base-0.8.0.dist-info/top_level.txt
openfisca_nsw_base-0.8.0.dist-info/RECORD
