Metadata-Version: 2.1
Name: openfisca-nsw-base
Version: 0.8.0
Summary: OpenFisca tax and benefit system for nsw - base package
Home-page: https://github.com/openfisca/country-template
Author: Sara Falamaki
Author-email: contact@openfisca.org
License: http://www.fsf.org/licensing/licenses/agpl-3.0.html
Keywords: benefit microsimulation social tax
Platform: UNKNOWN
Classifier: Development Status :: 5 - Production/Stable
Classifier: License :: OSI Approved :: GNU Affero General Public License v3
Classifier: Operating System :: POSIX
Classifier: Programming Language :: Python
Classifier: Topic :: Scientific/Engineering :: Information Analysis
Requires-Dist: OpenFisca-Core[web-api] (>=29.0)
Provides-Extra: dev
Requires-Dist: autopep8 (==1.4.0) ; extra == 'dev'
Requires-Dist: flake8 (<3.6.0,>=3.5.0) ; extra == 'dev'
Requires-Dist: flake8-print ; extra == 'dev'
Requires-Dist: pycodestyle (<2.4.0,>=2.3.0) ; extra == 'dev'
